MIPS32.v
module pipe_MIPS32 (clk1, clk2); 
 input clk1, clk2; // Two-phase clock 
 reg [31:0] PC, IF_ID_IR, IF_ID_NPC; 
 reg [31:0] ID_EX_IR, ID_EX_NPC, ID_EX_A, ID_EX_B, ID_EX_Imm; 
 reg [2:0] ID_EX_type, EX_MEM_type, MEM_WB_type; 
 reg [31:0] EX_MEM_IR, EX_MEM_ALUOut, EX_MEM_B; 
 reg EX_MEM_cond; 
 reg [31:0] MEM_WB_IR, MEM_WB_ALUOut, MEM_WB_LMD; 
 reg [31:0] Reg [0:31]; // Register bank (32 x 32) 
 reg [31:0] Mem [0:1023]; // 1024 x 32 memory
  parameter ADD_op=6'b000000;
  parameter SUB_op=6'b000001;
  parameter AND_op=6'b000010;
  parameter OR_op=6'b000011;
  parameter SLT_op=6'b000100;
  parameter MUL_op=6'b00010;
  parameter HLT_op=6'b111111;
  parameter LW_op=6'b001000;
  parameter SW_op=6'b001001;
  parameter ADDI_op=6'b001010;
  parameter SUBI_op=6'b001011;
  parameter SLTI_op=6'b001100;
  parameter BNEQZ_op=6'b001101;
  parameter BEQZ_op=6'b001110;
  parameter RR_ALU_op=3'b000;
  parameter RM_ALU_op=3'b001;
  parameter LOAD_op=3'b010;
  parameter STORE_op=3'b011;
  parameter BRANCH_op=3'b100;
  parameter HALT_op=3'b101;
  reg HALTED; 
 // Set after HLT instruction is completed (in WB stage) 
 reg TAKEN_BRANCH; 
 // Required to disable instructions after branch

always @(posedge clk1) // IF Stage 
 if (HALTED == 0) 
 begin 
 if (((EX_MEM_IR[31:26] == BEQZ_op) && (EX_MEM_cond == 1)) || 
 ((EX_MEM_IR[31:26] == BNEQZ_op) && (EX_MEM_cond == 0))) 
 begin 
 IF_ID_IR <= #2 Mem[EX_MEM_ALUOut]; 
 TAKEN_BRANCH <= #2 1'b1; 
 IF_ID_NPC <= #2 EX_MEM_ALUOut + 1; 
 PC <= #2 EX_MEM_ALUOut + 1; 
 end
 else 
 begin 
 IF_ID_IR <= #2 Mem[PC]; 
 IF_ID_NPC <= #2 PC + 1; 
 PC <= #2 PC + 1; 
 end 
 end

always @(posedge clk2) // ID Stage 
 if (HALTED == 0) 
 begin 
 if (IF_ID_IR[25:21] == 5'b00000) ID_EX_A <= 0; 
 else ID_EX_A <= #2 Reg[IF_ID_IR[25:21]]; // "rs" 
 if (IF_ID_IR[20:16] == 5'b00000) ID_EX_B <= 0; 
 else ID_EX_B <= #2 Reg[IF_ID_IR[20:16]]; // "rt" 
 ID_EX_NPC <= #2 IF_ID_NPC; 
 ID_EX_IR <= #2 IF_ID_IR; 
 ID_EX_Imm <= #2 {{16{IF_ID_IR[15]}}, {IF_ID_IR[15:0]}};

case (IF_ID_IR[31:26]) 
 ADD_op, SUB_op, AND_op, OR_op, SLT_op, MUL_op: ID_EX_type <= #2 RR_ALU_op; 
 ADDI_op, SUBI_op, SLTI_op: ID_EX_type <= #2 RM_ALU_op; 
 LW_op: ID_EX_type <= #2 LOAD_op; 
 SW_op: ID_EX_type <= #2 STORE_op; 
 BNEQZ_op, BEQZ_op: ID_EX_type <= #2 BRANCH_op; 
 HLT_op: ID_EX_type <= #2 HALT_op; 
 default: ID_EX_type <= #2 HALT_op; 
 // Invalid opcode
 endcase
 end

always @(posedge clk1) // EX Stage 
 if (HALTED == 0) 
 begin 
 EX_MEM_type <= #2 ID_EX_type; 
 EX_MEM_IR <= #2 ID_EX_IR; 
 TAKEN_BRANCH <= #2 0; 
 case (ID_EX_type) 
 RR_ALU_op: begin 
 case (ID_EX_IR[31:26]) // "opcode" 
 ADD_op: EX_MEM_ALUOut <= #2 ID_EX_A + ID_EX_B; 
 SUB_op: EX_MEM_ALUOut <= #2 ID_EX_A - ID_EX_B; 
 AND_op: EX_MEM_ALUOut <= #2 ID_EX_A & ID_EX_B; 
 OR_op: EX_MEM_ALUOut <= #2 ID_EX_A | ID_EX_B; 
 SLT_op: EX_MEM_ALUOut <= #2 ID_EX_A < ID_EX_B; 
 MUL_op: EX_MEM_ALUOut <= #2 ID_EX_A * ID_EX_B; 
 default: EX_MEM_ALUOut <= #2 32'hxxxxxxxx; 
 endcase
 end

RM_ALU_op: begin 
 case (ID_EX_IR[31:26]) // "opcode" 
 ADDI_op: EX_MEM_ALUOut <= #2 ID_EX_A + ID_EX_Imm; 
 SUBI_op: EX_MEM_ALUOut <= #2 ID_EX_A - ID_EX_Imm; 
 SLTI_op: EX_MEM_ALUOut <= #2 ID_EX_A < ID_EX_Imm; 
 default: EX_MEM_ALUOut <= #2 32'hxxxxxxxx; 
 endcase
 end

LOAD_op, STORE_op: 
 begin 
 EX_MEM_ALUOut <= #2 ID_EX_A + ID_EX_Imm; 
 EX_MEM_B <= #2 ID_EX_B; 
 end
 BRANCH_op: begin 
 EX_MEM_ALUOut <= #2 ID_EX_NPC + ID_EX_Imm; 
 EX_MEM_cond <= #2 (ID_EX_A == 0); 
 end 
 endcase
 end

always @(posedge clk2) // MEM Stage 
 if (HALTED == 0) 
 begin 
 MEM_WB_type <= EX_MEM_type; 
 MEM_WB_IR <= #2 EX_MEM_IR; 
 case (EX_MEM_type) 
 RR_ALU_op, RM_ALU_op: 
 MEM_WB_ALUOut <= #2 EX_MEM_ALUOut; 
 LOAD_op: MEM_WB_LMD <= #2 Mem[EX_MEM_ALUOut]; 
 STORE_op: if (TAKEN_BRANCH == 0) // Disable write 
 Mem[EX_MEM_ALUOut] <= #2 EX_MEM_B; 
 endcase
 end

always @(posedge clk1) // WB Stage 
 begin 
 if (TAKEN_BRANCH == 0) // Disable write if branch taken 
 case (MEM_WB_type) 
 RR_ALU_op: Reg[MEM_WB_IR[15:11]] <= #2 MEM_WB_ALUOut; // "rd" 
 RM_ALU_op: Reg[MEM_WB_IR[20:16]] <= #2 MEM_WB_ALUOut; // "rt" 
 LOAD_op: Reg[MEM_WB_IR[20:16]] <= #2 MEM_WB_LMD; // "rt" 
 HALT_op: HALTED <= #2 1'b1; 
 endcase
 end 
endmodule

test_bench_factorial.v
//File Name: MIPS32 RISC Processor_ test bench for Factorial operation
// Type: test_bench_example_2
// Department : Electrical engineering
// Author: Sagar
//Author's Email ID: guptasagar19965@gmail.com
// Purpose: ALU factorial opeartion with dummy instructions for avoiding hazards 
// Operation : factorial
// Date : 1 July 2023

`include "MIPS32.v"
module test_mips32; 
 reg clk1, clk2; 
 integer k; 
 pipe_MIPS32 mips (clk1, clk2); 
 initial 
 begin 
 clk1 = 0; clk2 = 0; 
 repeat (50) // Generating two-phase clock 
 begin 
 #5 clk1 = 1; #5 clk1 = 0; 
 #5 clk2 = 1; #5 clk2 = 0; 
 end 
 end 

initial 
 begin 
 for (k=0; k<31; k++) 
 mips.Reg[k] = k; 
 mips.Mem[0] = 32'h280a00c8; // ADDI R10,R0,200 
 mips.Mem[1] = 32'h28020001; // ADDI R2,R0,1 
 mips.Mem[2] = 32'h0e94a000; // OR R20,R20,R20 -- dummy instr. 
 mips.Mem[3] = 32'h21430000; // LW R3,0(R10) 
 mips.Mem[4] = 32'h0e94a000; // OR R20,R20,R20 -- dummy instr. 
 mips.Mem[5] = 32'h14431000; // Loop: MUL R2,R2,R3 
 mips.Mem[6] = 32'h2c630001; // SUBI R3,R3,1 
 mips.Mem[7] = 32'h0e94a000; // OR R20,R20,R20 -- dummy instr. 
 mips.Mem[8] = 32'h3460fffc; // BNEQZ R3,Loop (i.e. -4 offset) 
 mips.Mem[9] = 32'h2542fffe; // SW R2,-2(R10) 
 mips.Mem[10] = 32'hfc000000; // HLT

mips.Mem[200] = 7; // Find factorial of 7 
 mips.PC = 0; 
 mips.HALTED = 0; 
 mips.TAKEN_BRANCH = 0; 
 #2000 $display ("Mem[200] = %2d, Mem[198] = %6d", 
 mips.Mem[200], mips.Mem[198]); 
 end 
 initial 
 begin 
 $dumpfile ("mips_factorial.vcd"); 
 $dumpvars (0, test_mips32); 
 $monitor ("R2: %4d", mips.Reg[2]); 
 #300000 $finish; 
 end 
endmodule

mips_factorial.vcd
$date
	Fri Aug 25 03:24:18 2023
$end
$version
	Icarus Verilog
$end
$timescale
	1s
$end
$scope module test_mips32 $end
$var reg 1 ! clk1 $end
$var reg 1 " clk2 $end
$var integer 32 # k [31:0] $end
$scope module mips $end
$var wire 1 ! clk1 $end
$var wire 1 " clk2 $end
$var reg 32 $ EX_MEM_ALUOut [31:0] $end
$var reg 32 % EX_MEM_B [31:0] $end
$var reg 32 & EX_MEM_IR [31:0] $end
$var reg 1 ' EX_MEM_cond $end
$var reg 3 ( EX_MEM_type [2:0] $end
$var reg 1 ) HALTED $end
$var reg 32 * ID_EX_A [31:0] $end
$var reg 32 + ID_EX_B [31:0] $end
$var reg 32 , ID_EX_IR [31:0] $end
$var reg 32 - ID_EX_Imm [31:0] $end
$var reg 32 . ID_EX_NPC [31:0] $end
$var reg 3 / ID_EX_type [2:0] $end
$var reg 32 0 IF_ID_IR [31:0] $end
$var reg 32 1 IF_ID_NPC [31:0] $end
$var reg 32 2 MEM_WB_ALUOut [31:0] $end
$var reg 32 3 MEM_WB_IR [31:0] $end
$var reg 32 4 MEM_WB_LMD [31:0] $end
$var reg 3 5 MEM_WB_type [2:0] $end
$var reg 32 6 PC [31:0] $end
$var reg 1 7 TAKEN_BRANCH $end
$upscope $end
$upscope $end
$enddefinitions $end
#0
$dumpvars
07
b0 6
bx 5
bx 4
bx 3
bx 2
bx 1
bx 0
bx /
bx .
bx -
bx ,
bx +
bx *
0)
bx (
x'
bx &
bx %
bx $
b11111 #
0"
0!
$end
#5
1!
#7
b1 6
b1 1
b101000000010100000000011001000 0
#10
0!
#15
b0 *
1"
#17
b1 /
b11001000 -
b101000000010100000000011001000 ,
b1 .
b1010 +
#20
0"
#25
1!
#27
b11001000 $
b101000000010100000000011001000 &
b1 (
b10 6
b10 1
b101000000000100000000000000001 0
#30
0!
#35
b1 5
1"
#37
b11001000 2
b101000000010100000000011001000 3
b1 -
b101000000000100000000000000001 ,
b10 .
b10 +
#40
0"
#45
1!
#47
b11 6
b11 1
b1110100101001010000000000000 0
b1 $
b101000000000100000000000000001 &
#50
0!
#55
1"
#57
b0 /
b11111111111111111010000000000000 -
b1110100101001010000000000000 ,
b11 .
b10100 +
b10100 *
b1 2
b101000000000100000000000000001 3
#60
0"
#65
1!
#67
b10100 $
b1110100101001010000000000000 &
b0 (
b100 6
b100 1
b100001010000110000000000000000 0
#70
0!
#75
b0 5
1"
#77
b10100 2
b1110100101001010000000000000 3
b10 /
b0 -
b100001010000110000000000000000 ,
b100 .
b11 +
b11001000 *
#80
0"
#85
1!
#87
b101 6
b101 1
b1110100101001010000000000000 0
b11 %
b11001000 $
b100001010000110000000000000000 &
b10 (
#90
0!
#95
b10 5
1"
#97
b0 /
b11111111111111111010000000000000 -
b1110100101001010000000000000 ,
b101 .
b10100 +
b10100 *
b111 4
b100001010000110000000000000000 3
#100
0"
#105
1!
#107
b10100 $
b1110100101001010000000000000 &
b0 (
b110 6
b110 1
b10100010000110001000000000000 0
#110
0!
#115
b0 5
1"
#117
b1110100101001010000000000000 3
b1000000000000 -
b10100010000110001000000000000 ,
b110 .
b111 +
b1 *
#120
0"
#125
1!
#127
b111 6
b111 1
b101100011000110000000000000001 0
b111 $
b10100010000110001000000000000 &
#130
0!
#135
1"
#137
b1 /
b1 -
b101100011000110000000000000001 ,
b111 .
b111 *
b111 2
b10100010000110001000000000000 3
#140
0"
#145
1!
#147
b110 $
b101100011000110000000000000001 &
b1 (
b1000 6
b1000 1
b1110100101001010000000000000 0
#150
0!
#155
b1 5
1"
#157
b110 2
b101100011000110000000000000001 3
b0 /
b11111111111111111010000000000000 -
b1110100101001010000000000000 ,
b1000 .
b10100 +
b10100 *
#160
0"
#165
1!
#167
b1001 6
b1001 1
b110100011000001111111111111100 0
b10100 $
b1110100101001010000000000000 &
b0 (
#170
0!
#175
b0 +
b0 5
1"
#177
b100 /
b11111111111111111111111111111100 -
b110100011000001111111111111100 ,
b1001 .
b110 *
b10100 2
b1110100101001010000000000000 3
#180
0"
#185
1!
#187
0'
b101 $
b110100011000001111111111111100 &
b100 (
b1010 6
b1010 1
b100101010000101111111111111110 0
#190
0!
#195
b100 5
1"
#197
b110100011000001111111111111100 3
b11 /
b11111111111111111111111111111110 -
b100101010000101111111111111110 ,
b1010 .
b111 +
b11001000 *
#200
0"
#205
1!
#207
b110 6
b110 1
17
b10100010000110001000000000000 0
b111 %
b11000110 $
b100101010000101111111111111110 &
b11 (
#210
0!
#215
b11 5
1"
#217
b0 /
b1000000000000 -
b10100010000110001000000000000 ,
b110 .
b110 +
b111 *
b100101010000101111111111111110 3
#220
0"
#225
1!
#227
b101010 $
07
b10100010000110001000000000000 &
b0 (
b111 6
b111 1
b101100011000110000000000000001 0
#230
0!
#235
b0 5
1"
#237
b101010 2
b10100010000110001000000000000 3
b1 /
b1 -
b101100011000110000000000000001 ,
b111 .
b110 *
#240
0"
#245
1!
#247
b1000 6
b1000 1
b1110100101001010000000000000 0
b101 $
b101100011000110000000000000001 &
b1 (
#250
0!
#255
b1 5
1"
#257
b0 /
b11111111111111111010000000000000 -
b1110100101001010000000000000 ,
b1000 .
b10100 +
b10100 *
b101 2
b101100011000110000000000000001 3
#260
0"
#265
1!
#267
b10100 $
b1110100101001010000000000000 &
b0 (
b1001 6
b1001 1
b110100011000001111111111111100 0
#270
0!
#275
b0 5
b0 +
1"
#277
b10100 2
b1110100101001010000000000000 3
b100 /
b11111111111111111111111111111100 -
b110100011000001111111111111100 ,
b1001 .
b101 *
#280
0"
#285
1!
#287
b1010 6
b1010 1
b100101010000101111111111111110 0
b101 $
b110100011000001111111111111100 &
b100 (
#290
0!
#295
b100 5
1"
#297
b11 /
b11111111111111111111111111111110 -
b100101010000101111111111111110 ,
b1010 .
b101010 +
b11001000 *
b110100011000001111111111111100 3
#300
0"
#305
1!
#307
b101010 %
b11000110 $
b100101010000101111111111111110 &
b11 (
b110 6
b110 1
07
b10100010000110001000000000000 0
#310
0!
#315
b11 5
1"
#317
b100101010000101111111111111110 3
b0 /
b1000000000000 -
b10100010000110001000000000000 ,
b110 .
b101 +
b101010 *
#320
0"
#325
1!
#327
b111 6
b111 1
b101100011000110000000000000001 0
b11010010 $
b10100010000110001000000000000 &
b0 (
#330
0!
#335
b0 5
1"
#337
b1 /
b1 -
b101100011000110000000000000001 ,
b111 .
b101 *
b11010010 2
b10100010000110001000000000000 3
#340
0"
#345
1!
#347
b100 $
b101100011000110000000000000001 &
b1 (
b1000 6
b1000 1
b1110100101001010000000000000 0
#350
0!
#355
b1 5
1"
#357
b100 2
b101100011000110000000000000001 3
b0 /
b11111111111111111010000000000000 -
b1110100101001010000000000000 ,
b1000 .
b10100 +
b10100 *
#360
0"
#365
1!
#367
b1001 6
b1001 1
b110100011000001111111111111100 0
b10100 $
b1110100101001010000000000000 &
b0 (
#370
0!
#375
b0 +
b0 5
1"
#377
b100 /
b11111111111111111111111111111100 -
b110100011000001111111111111100 ,
b1001 .
b100 *
b10100 2
b1110100101001010000000000000 3
#380
0"
#385
1!
#387
b101 $
b110100011000001111111111111100 &
b100 (
b1010 6
b1010 1
b100101010000101111111111111110 0
#390
0!
#395
b100 5
1"
#397
b110100011000001111111111111100 3
b11 /
b11111111111111111111111111111110 -
b100101010000101111111111111110 ,
b1010 .
b11010010 +
b11001000 *
#400
0"
#405
1!
#407
b110 6
b110 1
17
b10100010000110001000000000000 0
b11010010 %
b11000110 $
b100101010000101111111111111110 &
b11 (
#410
0!
#415
b11 5
1"
#417
b0 /
b1000000000000 -
b10100010000110001000000000000 ,
b110 .
b100 +
b11010010 *
b100101010000101111111111111110 3
#420
0"
#425
1!
#427
b1101001000 $
07
b10100010000110001000000000000 &
b0 (
b111 6
b111 1
b101100011000110000000000000001 0
#430
0!
#435
b0 5
1"
#437
b1101001000 2
b10100010000110001000000000000 3
b1 /
b1 -
b101100011000110000000000000001 ,
b111 .
b100 *
#440
0"
#445
1!
#447
b1000 6
b1000 1
b1110100101001010000000000000 0
b11 $
b101100011000110000000000000001 &
b1 (
#450
0!
#455
b1 5
1"
#457
b0 /
b11111111111111111010000000000000 -
b1110100101001010000000000000 ,
b1000 .
b10100 +
b10100 *
b11 2
b101100011000110000000000000001 3
#460
0"
#465
1!
#467
b10100 $
b1110100101001010000000000000 &
b0 (
b1001 6
b1001 1
b110100011000001111111111111100 0
#470
0!
#475
b0 5
b0 +
1"
#477
b10100 2
b1110100101001010000000000000 3
b100 /
b11111111111111111111111111111100 -
b110100011000001111111111111100 ,
b1001 .
b11 *
#480
0"
#485
1!
#487
b1010 6
b1010 1
b100101010000101111111111111110 0
b101 $
b110100011000001111111111111100 &
b100 (
#490
0!
#495
b100 5
1"
#497
b11 /
b11111111111111111111111111111110 -
b100101010000101111111111111110 ,
b1010 .
b1101001000 +
b11001000 *
b110100011000001111111111111100 3
#500
0"
#505
1!
#507
b1101001000 %
b11000110 $
b100101010000101111111111111110 &
b11 (
b110 6
b110 1
07
b10100010000110001000000000000 0
#510
0!
#515
b11 5
1"
#517
b100101010000101111111111111110 3
b0 /
b1000000000000 -
b10100010000110001000000000000 ,
b110 .
b11 +
b1101001000 *
#520
0"
#525
1!
#527
b111 6
b111 1
b101100011000110000000000000001 0
b100111011000 $
b10100010000110001000000000000 &
b0 (
#530
0!
#535
b0 5
1"
#537
b1 /
b1 -
b101100011000110000000000000001 ,
b111 .
b11 *
b100111011000 2
b10100010000110001000000000000 3
#540
0"
#545
1!
#547
b10 $
b101100011000110000000000000001 &
b1 (
b1000 6
b1000 1
b1110100101001010000000000000 0
#550
0!
#555
b1 5
1"
#557
b10 2
b101100011000110000000000000001 3
b0 /
b11111111111111111010000000000000 -
b1110100101001010000000000000 ,
b1000 .
b10100 +
b10100 *
#560
0"
#565
1!
#567
b1001 6
b1001 1
b110100011000001111111111111100 0
b10100 $
b1110100101001010000000000000 &
b0 (
#570
0!
#575
b0 +
b0 5
1"
#577
b100 /
b11111111111111111111111111111100 -
b110100011000001111111111111100 ,
b1001 .
b10 *
b10100 2
b1110100101001010000000000000 3
#580
0"
#585
1!
#587
b101 $
b110100011000001111111111111100 &
b100 (
b1010 6
b1010 1
b100101010000101111111111111110 0
#590
0!
#595
b100 5
1"
#597
b110100011000001111111111111100 3
b11 /
b11111111111111111111111111111110 -
b100101010000101111111111111110 ,
b1010 .
b100111011000 +
b11001000 *
#600
0"
#605
1!
#607
b110 6
b110 1
17
b10100010000110001000000000000 0
b100111011000 %
b11000110 $
b100101010000101111111111111110 &
b11 (
#610
0!
#615
b11 5
1"
#617
b0 /
b1000000000000 -
b10100010000110001000000000000 ,
b110 .
b10 +
b100111011000 *
b100101010000101111111111111110 3
#620
0"
#625
1!
#627
b1001110110000 $
07
b10100010000110001000000000000 &
b0 (
b111 6
b111 1
b101100011000110000000000000001 0
#630
0!
#635
b0 5
1"
#637
b1001110110000 2
b10100010000110001000000000000 3
b1 /
b1 -
b101100011000110000000000000001 ,
b111 .
b10 *
#640
0"
#645
1!
#647
b1000 6
b1000 1
b1110100101001010000000000000 0
b1 $
b101100011000110000000000000001 &
b1 (
#650
0!
#655
b1 5
1"
#657
b0 /
b11111111111111111010000000000000 -
b1110100101001010000000000000 ,
b1000 .
b10100 +
b10100 *
b1 2
b101100011000110000000000000001 3
#660
0"
#665
1!
#667
b10100 $
b1110100101001010000000000000 &
b0 (
b1001 6
b1001 1
b110100011000001111111111111100 0
#670
0!
#675
b0 5
b0 +
1"
#677
b10100 2
b1110100101001010000000000000 3
b100 /
b11111111111111111111111111111100 -
b110100011000001111111111111100 ,
b1001 .
b1 *
#680
0"
#685
1!
#687
b1010 6
b1010 1
b100101010000101111111111111110 0
b101 $
b110100011000001111111111111100 &
b100 (
#690
0!
#695
b100 5
1"
#697
b11 /
b11111111111111111111111111111110 -
b100101010000101111111111111110 ,
b1010 .
b1001110110000 +
b11001000 *
b110100011000001111111111111100 3
#700
0"
#705
1!
#707
b1001110110000 %
b11000110 $
b100101010000101111111111111110 &
b11 (
b110 6
b110 1
07
b10100010000110001000000000000 0
#710
0!
#715
b11 5
1"
#717
b100101010000101111111111111110 3
b0 /
b1000000000000 -
b10100010000110001000000000000 ,
b110 .
b1 +
b1001110110000 *
#720
0"
#725
1!
#727
b111 6
b111 1
b101100011000110000000000000001 0
b1001110110000 $
b10100010000110001000000000000 &
b0 (
#730
0!
#735
b0 5
1"
#737
b1 /
b1 -
b101100011000110000000000000001 ,
b111 .
b1 *
b1001110110000 2
b10100010000110001000000000000 3
#740
0"
#745
1!
#747
b0 $
b101100011000110000000000000001 &
b1 (
b1000 6
b1000 1
b1110100101001010000000000000 0
#750
0!
#755
b1 5
1"
#757
b0 2
b101100011000110000000000000001 3
b0 /
b11111111111111111010000000000000 -
b1110100101001010000000000000 ,
b1000 .
b10100 +
b10100 *
#760
0"
#765
1!
#767
b1001 6
b1001 1
b110100011000001111111111111100 0
b10100 $
b1110100101001010000000000000 &
b0 (
#770
0!
#775
b0 +
b0 5
1"
#777
b100 /
b11111111111111111111111111111100 -
b110100011000001111111111111100 ,
b1001 .
b0 *
b10100 2
b1110100101001010000000000000 3
#780
0"
#785
1!
#787
1'
b101 $
b110100011000001111111111111100 &
b100 (
b1010 6
b1010 1
b100101010000101111111111111110 0
#790
0!
#795
b100 5
1"
#797
b110100011000001111111111111100 3
b11 /
b11111111111111111111111111111110 -
b100101010000101111111111111110 ,
b1010 .
b1001110110000 +
b11001000 *
#800
0"
#805
1!
#807
b1011 6
b1011 1
b11111100000000000000000000000000 0
b11000110 $
b100101010000101111111111111110 &
b11 (
#810
0!
#815
b0 +
b0 *
b11 5
1"
#817
b101 /
b0 -
b11111100000000000000000000000000 ,
b1011 .
b100101010000101111111111111110 3
#820
0"
#825
1!
#827
b11111100000000000000000000000000 &
b101 (
b1100 6
b1100 1
bx 0
#830
0!
#835
b101 5
1"
#837
b11111100000000000000000000000000 3
bx -
bx ,
b1100 .
bx +
bx *
#840
0"
#845
1!
#847
b1101 6
b1101 1
bx &
1)
